nrpy/__init__.py
nrpy/c_codegen.py
nrpy/c_function.py
nrpy/finite_difference.py
nrpy/grid.py
nrpy/indexedexp.py
nrpy/params.py
nrpy/py.typed
nrpy/reference_metric.py
nrpy/equations/__init__.py
nrpy/equations/general_relativity/ADM_to_BSSN.py
nrpy/equations/general_relativity/BSSN_RHSs.py
nrpy/equations/general_relativity/BSSN_constraints.py
nrpy/equations/general_relativity/BSSN_gauge_RHSs.py
nrpy/equations/general_relativity/BSSN_quantities.py
nrpy/equations/general_relativity/BSSN_to_ADM.py
nrpy/equations/general_relativity/InitialData_Cartesian.py
nrpy/equations/general_relativity/InitialData_Spherical.py
nrpy/equations/general_relativity/LorentzBoost.py
nrpy/equations/general_relativity/T4munu.py
nrpy/equations/general_relativity/__init__.py
nrpy/equations/general_relativity/g4munu_conversions.py
nrpy/equations/general_relativity/psi4.py
nrpy/equations/general_relativity/psi4_tetrads.py
nrpy/equations/general_relativity/nrpylatex/__init__.py
nrpy/equations/general_relativity/nrpylatex/test_parse_BSSN.py
nrpy/equations/nrpyelliptic/CommonParams.py
nrpy/equations/nrpyelliptic/ConformallyFlat_RHSs.py
nrpy/equations/nrpyelliptic/ConformallyFlat_SourceTerms.py
nrpy/equations/nrpyelliptic/__init__.py
nrpy/equations/quaternion_rotations/__init__.py
nrpy/equations/quaternion_rotations/tensor_rotation.py
nrpy/equations/seobnr/SEOBNRv5_aligned_spin_Hamiltonian.py
nrpy/equations/seobnr/__init__.py
nrpy/equations/special_functions/__init__.py
nrpy/equations/special_functions/spin_weighted_spherical_harmonics.py
nrpy/equations/wave_equation/CommonParams.py
nrpy/equations/wave_equation/WaveEquationCurvilinear_RHSs.py
nrpy/equations/wave_equation/WaveEquation_RHSs.py
nrpy/equations/wave_equation/WaveEquation_Solutions_InitialData.py
nrpy/equations/wave_equation/__init__.py
nrpy/examples/__init__.py
nrpy/examples/blackhole_spectroscopy.py
nrpy/examples/carpet_baikal_thorns.py
nrpy/examples/carpet_wavetoy_thorns.py
nrpy/examples/carpetx_baikal_thorns.py
nrpy-2.1.0.dist-info/LICENSE
nrpy-2.1.0.dist-info/METADATA
nrpy-2.1.0.dist-info/WHEEL
nrpy-2.1.0.dist-info/top_level.txt
nrpy-2.1.0.dist-info/RECORD
